dovcha/__init__.py
dovcha/app.py
dovcha/middleware.py
dovcha/orm.py
dovcha/response.py
dovcha-0.2.0.dist-info/METADATA
dovcha-0.2.0.dist-info/WHEEL
dovcha-0.2.0.dist-info/top_level.txt
dovcha-0.2.0.dist-info/RECORD
