Metadata-Version: 2.4
Name: dovcha
Version: 0.2.0
Summary: A simple Python web framework for building web applications.
Home-page: https://github.com/me/myproject
Author: Mustafo Buriev
Author-email: boriyevmustafo722@gmail.com
License: MIT
Classifier: License :: OSI Approved :: MIT License
Classifier: Programming Language :: Python
Classifier: Programming Language :: Python :: 3
Classifier: Programming Language :: Python :: 3.6
Classifier: Programming Language :: Python :: Implementation :: CPython
Classifier: Programming Language :: Python :: Implementation :: PyPy
Requires-Python: >=3.9.0
Requires-Dist: Jinja2==3.1.6
Requires-Dist: parse==1.20.2
Requires-Dist: requests==2.32.3
Requires-Dist: requests-wsgi-adapter==0.4.1
Requires-Dist: WebOb==1.8.9
Requires-Dist: whitenoise==6.9.0
Dynamic: author
Dynamic: author-email
Dynamic: classifier
Dynamic: description
Dynamic: description-content-type
Dynamic: home-page
Dynamic: license
Dynamic: requires-dist
Dynamic: requires-python
Dynamic: summary
